backslash_markdown_extension/__init__.py
backslash_markdown_extension/processors.py
backslash_markdown_extension-0.1.14.dist-info/METADATA
backslash_markdown_extension-0.1.14.dist-info/WHEEL
backslash_markdown_extension-0.1.14.dist-info/top_level.txt
backslash_markdown_extension-0.1.14.dist-info/RECORD
