Metadata-Version: 2.1
Name: backslash-markdown-extension
Version: 0.1.14
Summary: Backslash Markdown Extension
Home-page: https://github.com/gduverger/backslash-markdown-extension
Author: Georges Duverger
Author-email: georges.duverger@gmail.com
License: MIT
Platform: UNKNOWN
Classifier: Programming Language :: Python :: 3
Classifier: License :: OSI Approved :: MIT License
Classifier: Operating System :: OS Independent
Classifier: Intended Audience :: Developers
Classifier: Natural Language :: English
Requires-Python: >=3
Requires-Dist: markdown
